CHANGELOG.rst
CONTRIBUTORS.rst
LICENSE.txt
MANIFEST.in
README.rst
requirements.txt
setup.py
src/edeposit/__init__.py
src/edeposit.amqp.marcxml2mods.egg-info/PKG-INFO
src/edeposit.amqp.marcxml2mods.egg-info/SOURCES.txt
src/edeposit.amqp.marcxml2mods.egg-info/dependency_links.txt
src/edeposit.amqp.marcxml2mods.egg-info/namespace_packages.txt
src/edeposit.amqp.marcxml2mods.egg-info/not-zip-safe
src/edeposit.amqp.marcxml2mods.egg-info/requires.txt
src/edeposit.amqp.marcxml2mods.egg-info/top_level.txt
src/edeposit/amqp/__init__.py
src/edeposit/amqp/marcxml2mods/__init__.py
src/edeposit/amqp/marcxml2mods/structures/__init__.py
src/edeposit/amqp/marcxml2mods/structures/requests.py
src/edeposit/amqp/marcxml2mods/structures/responses.py
tests/oai_example.oai
tests/test_amqp_chain.py
tests/transformed_mods.xml