Metadata-Version: 1.1
Name: edeposit.amqp.marcxml2mods
Version: 0.1.0
Summary: Edeposit's AMQP service for converting MARC XML to MODS.
Home-page: https://github.com/edeposit/edeposit.amqp.marcxml2mods
Author: Edeposit team
Author-email: edeposit@email.cz
License: MIT
Platform: UNKNOWN
Classifier: Development Status :: 3 - Alpha
Classifier: Intended Audience :: Developers
Classifier: Programming Language :: Python :: 2
Classifier: Programming Language :: Python :: 2.7
Classifier: License :: OSI Approved :: MIT License
